odoo/addons/multi_step_wizard/README.rst
odoo/addons/multi_step_wizard/__init__.py
odoo/addons/multi_step_wizard/__manifest__.py
odoo/addons/multi_step_wizard/i18n/hr.po
odoo/addons/multi_step_wizard/i18n/multi_step_wizard.pot
odoo/addons/multi_step_wizard/i18n/zh_CN.po
odoo/addons/multi_step_wizard/models/__init__.py
odoo/addons/multi_step_wizard/models/multi_step_wizard.py
odoo/addons/multi_step_wizard/readme/CONTRIBUTORS.rst
odoo/addons/multi_step_wizard/readme/DESCRIPTION.rst
odoo/addons/multi_step_wizard/readme/USAGE.rst
odoo/addons/multi_step_wizard/static/description/icon.png
odoo/addons/multi_step_wizard/static/description/index.html
odoo/addons/multi_step_wizard/tests/__init__.py
odoo/addons/multi_step_wizard/tests/multi_step_wizard_test.py
odoo/addons/multi_step_wizard/tests/test_multi_step_wizard.py
odoo/addons/multi_step_wizard/views/multi_step_wizard_views.xml
odoo13_addon_multi_step_wizard-13.0.1.1.2.dist-info/METADATA
odoo13_addon_multi_step_wizard-13.0.1.1.2.dist-info/WHEEL
odoo13_addon_multi_step_wizard-13.0.1.1.2.dist-info/top_level.txt
odoo13_addon_multi_step_wizard-13.0.1.1.2.dist-info/RECORD
